voo_evasion/__init__.py
voo_evasion/__main__.py
voo_evasion/evasion_keys.json
voo_evasion/voo_evasion.py
voo_evasion-0.0.1.dist-info/LICENSE
voo_evasion-0.0.1.dist-info/METADATA
voo_evasion-0.0.1.dist-info/WHEEL
voo_evasion-0.0.1.dist-info/top_level.txt
voo_evasion-0.0.1.dist-info/RECORD
