Metadata-Version: 2.1
Name: voo-evasion
Version: 0.0.1
Summary: A Python module for the .évasion box.
Home-page: https://github.com/2010019970909/voo-tv
Author: Vincent Stragier
Author-email: vincent.stragier@outlook.com
License: UNKNOWN
Project-URL: Bug Tracker, https://github.com/2010019970909/voo-tv/issues
Platform: UNKNOWN
Classifier: Programming Language :: Python :: 3
Classifier: License :: OSI Approved :: GNU General Public License v3 (GPLv3)
Classifier: Operating System :: OS Independent
Requires-Python: <4,>=3.6
License-File: LICENSE
Requires-Dist: requests (>=2.27.1)
Requires-Dist: netifaces (>=0.11.0)
